fastapi_scaffold/__init__.py
fastapi_scaffold/cli.py
fastapi_scaffold/templates.py
fastapi_scaffold/utils.py
fastapi_scaffold-0.2.1.dist-info/LICENSE
fastapi_scaffold-0.2.1.dist-info/METADATA
fastapi_scaffold-0.2.1.dist-info/WHEEL
fastapi_scaffold-0.2.1.dist-info/entry_points.txt
fastapi_scaffold-0.2.1.dist-info/top_level.txt
fastapi_scaffold-0.2.1.dist-info/RECORD
