Metadata-Version: 2.2
Name: fastapi-scaffold
Version: 0.2.1
Summary: A CLI tool to scaffold FastAPI projects with ML, DB, Auth, and Docker options.
Home-page: https://github.com/devroopsaha744/fastapi-scaffold
Author: Devroop Saha
Author-email: Devroop Saha <devroopsaha844@gmail.com>
License: MIT
Classifier: Programming Language :: Python :: 3
Classifier: License :: OSI Approved :: MIT License
Classifier: Operating System :: OS Independent
Requires-Python: >=3.7
License-File: LICENSE
Requires-Dist: click
Dynamic: author
Dynamic: home-page
Dynamic: requires-python
